[
  {
    "id": "I-01",
    "ingredient": "BUTTER",
    "amount": 25
  },
  {
    "id": "I-02",
    "ingredient": "FLOUR",
    "amount": 25
  },
  {
    "id": "I-03",
    "ingredient": "CHOCOLATE_CHIP",
    "amount": 25
  },
  {
    "id": "I-04",
    "ingredient": "ALMOND",
    "amount": 25
  },
  {
    "id": "I-05",
    "ingredient": "BLUEBERRY",
    "amount": 25
  },
  {
    "id": "I-06",
    "ingredient": "STRAWBERRY",
    "amount": 25
  },
  {
    "id": "I-07",
    "ingredient": "OATMEAL",
    "amount": 25
  },
  {
    "id": "I-08",
    "ingredient": "RAISIN",
    "amount": 25
  },
  {
    "id": "I-09",
    "ingredient": "SUGAR",
    "amount": 25
  },
  {
    "id": "I-10",
    "ingredient": "MILK",
    "amount": 25
  },
  {
    "id": "I-11",
    "ingredient": "OAT_MILK",
    "amount": 25
  },
  {
    "id": "I-12",
    "ingredient": "ALMOND_MILK",
    "amount": 25
  },
  {
    "id": "I-13",
    "ingredient": "SUGAR_FREE_SYRUP",
    "amount": 25
  },
  {
    "id": "I-14",
    "ingredient": "TEA_LEAVES_BLACK",
    "amount": 25
  },
  {
    "id": "I-15",
    "ingredient": "TEA_LEAVES_GREEN",
    "amount": 25
  },
  {
    "id": "I-16",
    "ingredient": "TEA_LEAVES_HERBAL",
    "amount": 25
  },
  {
    "id": "I-17",
    "ingredient": "COFFEE_BEAN",
    "amount": 25
  },
  {
    "id": "I-18",
    "ingredient": "DECAF_COFFEE_BEAN",
    "amount": 25
  },
  {
    "id": "I-19",
    "ingredient": "DECAF_TEA_LEAVES_BLACK",
    "amount": 25
  }
]